powerfuldeveloper_psutils/__init__.py
powerfuldeveloper_psutils/docker/__init__.py
powerfuldeveloper_psutils/docker/docker_processor.py
powerfuldeveloper_psutils-0.0.5.dist-info/LICENSE
powerfuldeveloper_psutils-0.0.5.dist-info/METADATA
powerfuldeveloper_psutils-0.0.5.dist-info/WHEEL
powerfuldeveloper_psutils-0.0.5.dist-info/top_level.txt
powerfuldeveloper_psutils-0.0.5.dist-info/RECORD
