Metadata-Version: 2.1
Name: powerfuldeveloper-psutils
Version: 0.0.5
Summary: You can use this to control command line based stuff
Home-page: UNKNOWN
Author: Hussein Mirzaki
Author-email: husseinmirzaki@gmail.com
License: UNKNOWN
Platform: UNKNOWN
Classifier: Programming Language :: Python :: 3
Classifier: License :: OSI Approved :: MIT License
Requires-Python: >=3.7
Requires-Dist: powerfuldeveloper-base (==0.0.6)
